{
  "sections": {
    "main": {
      "type": "main-article",
      "disabled": true,
      "blocks": {
        "featured_image": {
          "type": "featured_image",
          "settings": {
            "image_height": "adapt"
          }
        },
        "title": {
          "type": "title",
          "settings": {
            "blog_show_date": true,
            "blog_show_author": false
          }
        },
        "share": {
          "type": "share",
          "settings": {
            "share_label": "Share"
          }
        },
        "content": {
          "type": "content",
          "settings": {
          }
        }
      },
      "block_order": [
        "featured_image",
        "title",
        "share",
        "content"
      ],
      "settings": {
      }
    },
    "16559742803aaa6577": {
      "type": "loop-article-banner",
      "settings": {
        "image_height": "small"
      }
    },
    "1658122483d764eac3": {
      "type": "loop-article-author",
      "settings": {
        "author_prefix": "By:"
      }
    },
    "206550a5-73db-4a85-bf30-dc6c1c292d48": {
      "type": "rich-text",
      "blocks": {
        "template--15826134302916__206550a5-73db-4a85-bf30-dc6c1c292d48-16752485096357b5bf-0": {
          "type": "heading",
          "settings": {
            "heading": "Key takeaways",
            "heading_size": "h2"
          }
        },
        "template--15826134302916__206550a5-73db-4a85-bf30-dc6c1c292d48-16752485096357b5bf-1": {
          "type": "text",
          "settings": {
            "text": "<ul><li>Noise anxiety comes in many forms, with the most common types of noise sensitivity being phonophobia, misophonia and hyperacusis<\/li><li>You may not be able to completely cure noise anxiety<\/li><li>But there are lots of ways to manage your noise anxiety, including sound therapy, CBT, support groups and stress management<\/li><\/ul>",
            "description_padding": 32
          }
        },
        "template--15826134302916__206550a5-73db-4a85-bf30-dc6c1c292d48-16752485096357b5bf-2": {
          "type": "button",
          "settings": {
            "button_label": "Discover Loop Earplugs",
            "button_link": "shopify:\/\/collections\/all",
            "button_bgcolor_1": "",
            "button_txtcolor_1": "",
            "button_style_secondary": false,
            "button_label_2": "",
            "button_link_2": "",
            "button_bgcolor_2": "",
            "button_txtcolor_2": "",
            "button_style_secondary_2": false,
            "button_padding": 32
          }
        }
      },
      "block_order": [
        "template--15826134302916__206550a5-73db-4a85-bf30-dc6c1c292d48-16752485096357b5bf-0",
        "template--15826134302916__206550a5-73db-4a85-bf30-dc6c1c292d48-16752485096357b5bf-1",
        "template--15826134302916__206550a5-73db-4a85-bf30-dc6c1c292d48-16752485096357b5bf-2"
      ],
      "settings": {
        "desktop_content_position": "center",
        "content_alignment": "left",
        "color_scheme": "background-2",
        "full_width": true,
        "decription_max_width": 100,
        "padding_top": 44,
        "padding_bottom": 44
      }
    },
    "c1914074-e112-47ac-8be5-71e50691e7b4": {
      "type": "rich-text",
      "blocks": {
        "template--15826134302916__c1914074-e112-47ac-8be5-71e50691e7b4-16752485096357b5bf-1": {
          "type": "text",
          "settings": {
            "text": "<p>Do loud environments often make you feel panicked or overwhelmed? Well, you’re not alone. Noise anxiety is a common issue, and while different people experience it to varying degrees, it can be difficult to deal with for anyone.<\/p><p>For some people, anxiety can be triggered by unexpected noises such as fireworks, backfiring cars, or sudden shouting. For others, simple everyday sounds such as chewing, music, and coughing can cause significant distress. At the more extreme end of the scale, <a href=\"https:\/\/www.loopearplugs.com\/blogs\/blog\/sensitivity-to-sound-how-to-deal-with-noise-sensitivity\"><span style=\"text-decoration:underline\">noise sensitivity issues<\/span><\/a> can have a big impact on people’s lives, leading them to avoid certain situations and become socially isolated.<\/p><p>But you don’t need to resign yourself to living a life of anxiety and sensitivity to noise. Let’s take a look at the most common kinds of noise anxiety and how to cope with noise anxiety so you can live a more comfortable life.<\/p>",
            "description_padding": 32
          }
        }
      },
      "block_order": [
        "template--15826134302916__c1914074-e112-47ac-8be5-71e50691e7b4-16752485096357b5bf-1"
      ],
      "settings": {
        "desktop_content_position": "center",
        "content_alignment": "left",
        "color_scheme": "background-1",
        "full_width": true,
        "decription_max_width": 100,
        "padding_top": 44,
        "padding_bottom": 44
      }
    },
    "16581501774a32acf8": {
      "type": "loop-article-img-txt",
      "blocks": {
        "15d54bfe-1b48-43c0-9fad-0527a7874216": {
          "type": "heading",
          "settings": {
            "heading": "Common types of sound sensitivity and anxiety",
            "heading_size": "h2"
          }
        },
        "16581501770ad7ecad-1": {
          "type": "text",
          "settings": {
            "text": "<p>There are several types of sensitivity and anxiety caused by loud and distressing noises, some of which have overlapping symptoms. Some of the most common include:<\/p>",
            "text_style": "body"
          }
        }
      },
      "block_order": [
        "15d54bfe-1b48-43c0-9fad-0527a7874216",
        "16581501770ad7ecad-1"
      ],
      "settings": {
        "image": "shopify:\/\/shop_images\/LP_Noise_1.jpg",
        "video_url": "",
        "video-tag": "",
        "height": "small",
        "desktop_image_width": "medium",
        "layout": "image_first",
        "desktop_content_position": "top",
        "desktop_content_alignment": "left",
        "content_layout": "no-overlap",
        "color_scheme": "#ffffff",
        "mobile_content_alignment": "left",
        "padding_top": 44,
        "padding_bottom": 44
      }
    },
    "16604607234acd9044": {
      "type": "rich-text",
      "blocks": {
        "1c50e393-e4fc-41cc-8d7a-88a2d8d03645": {
          "type": "heading",
          "settings": {
            "heading": "<h3>Phonophobia<\/h3>",
            "heading_size": "h2"
          }
        },
        "78c0a6cd-ae4d-4cdb-8feb-89d03f65ec8d": {
          "type": "text",
          "settings": {
            "text": "<p><a href=\"https:\/\/www.loopearplugs.com\/blogs\/blog\/how-to-overcome-phonophobia\"><span style=\"text-decoration:underline\">Phonophobia<\/span><\/a>, or fear of noise, is characterized by anxiety in the presence of loud noises. This could include anything from applause to passing vehicles, music, shouting, and more. Understandably, this can make crowded areas and social situations very difficult for people with phonophobia to deal with. <\/p><p>If you have this condition, your phobia of loud noises can cause great distress and anxiety. If you avoid social situations because you’re worried about hearing triggering noises, you may find yourself feeling isolated – and there’s a chance that by avoiding noises that make you feel anxious, you may make your reactions even more intense when you do encounter such noises.<\/p>",
            "description_padding": 32
          }
        },
        "0af38481-ffb1-4074-b1f0-8ebd719964fd": {
          "type": "heading",
          "settings": {
            "heading": "<h3>Misophonia<\/h3>",
            "heading_size": "h2"
          }
        },
        "8720fd58-205b-4bf5-b987-252ac7701d2a": {
          "type": "text",
          "settings": {
            "text": "<p>Misophonia is a condition which triggers feelings of repulsion and anger in response to noises made by others. People with misophonia become intensely angry at certain sounds, which vary from person to person, but chewing, finger tapping and coughing are some of the most common. They might get sweaty palms, an increased heart rate, and feel angry, annoyed, disgusted or distressed.<\/p><p>This can cause lots of stress for people with misophonia. They may avoid social situations, and relationships with friends, family and colleagues may become strained if noises made by others are a recurring issue.<\/p>",
            "description_padding": 32
          }
        },
        "fe1aba0f-8e58-4685-8919-0bd94a258c19": {
          "type": "heading",
          "settings": {
            "heading": "<h3>Hyperacusis<\/h3>",
            "heading_size": "h2"
          }
        },
        "222a8d34-fd98-4a0e-b2e2-fdac4e60fda7": {
          "type": "text",
          "settings": {
            "text": "<p>Hyperacusis, or noise sensitivity, is an extreme sensitivity to sound where noises that seem to be at a normal level to other people can cause pain or discomfort. It can cause anxiety with loud noises, meaning people with hyperacusis may avoid putting themselves in situations where they’re likely to hear loud noises. <\/p><p>That can lead to isolation and stress, and may become a vicious cycle in which someone wants to avoid loud noises so they isolate themselves in a very quiet environment, which then only makes noises seem even louder.<\/p>",
            "description_padding": 32
          }
        }
      },
      "block_order": [
        "1c50e393-e4fc-41cc-8d7a-88a2d8d03645",
        "78c0a6cd-ae4d-4cdb-8feb-89d03f65ec8d",
        "0af38481-ffb1-4074-b1f0-8ebd719964fd",
        "8720fd58-205b-4bf5-b987-252ac7701d2a",
        "fe1aba0f-8e58-4685-8919-0bd94a258c19",
        "222a8d34-fd98-4a0e-b2e2-fdac4e60fda7"
      ],
      "settings": {
        "desktop_content_position": "center",
        "content_alignment": "left",
        "color_scheme": "background-1",
        "full_width": true,
        "decription_max_width": 100,
        "padding_top": 16,
        "padding_bottom": 44
      }
    },
    "fd43e1f8-2931-404c-b7b9-2f56c8f3afbc": {
      "type": "image-banner",
      "blocks": {
        "template--15826134302916__fd43e1f8-2931-404c-b7b9-2f56c8f3afbc-1675250031cde3231e-0": {
          "type": "heading",
          "disabled": true,
          "settings": {
            "heading": "Image banner",
            "heading_size": "h1"
          }
        },
        "template--15826134302916__fd43e1f8-2931-404c-b7b9-2f56c8f3afbc-1675250031cde3231e-1": {
          "type": "text",
          "disabled": true,
          "settings": {
            "text": "Give customers details about the banner image(s) or content on the template.",
            "richtext": "",
            "text_style": "body"
          }
        },
        "template--15826134302916__fd43e1f8-2931-404c-b7b9-2f56c8f3afbc-1675250031cde3231e-2": {
          "type": "buttons",
          "disabled": true,
          "settings": {
            "button_label_1": "Button label",
            "button_link_1": "",
            "button_style_secondary_1": false,
            "button_bgcolor_1": "",
            "button_txtcolor_1": "",
            "button_label_2": "Button label",
            "button_link_2": "",
            "button_style_secondary_2": false,
            "button_bgcolor_2": "",
            "button_txtcolor_2": "",
            "button_label_3": "Button label",
            "show_id": ""
          }
        }
      },
      "block_order": [
        "template--15826134302916__fd43e1f8-2931-404c-b7b9-2f56c8f3afbc-1675250031cde3231e-0",
        "template--15826134302916__fd43e1f8-2931-404c-b7b9-2f56c8f3afbc-1675250031cde3231e-1",
        "template--15826134302916__fd43e1f8-2931-404c-b7b9-2f56c8f3afbc-1675250031cde3231e-2"
      ],
      "settings": {
        "image": "shopify:\/\/shop_images\/give-your-ears-a-rest-with-loops.webp",
        "lazyload": true,
        "image_overlay_opacity": 0,
        "image_height": "small",
        "margin_top": true,
        "adapt_height_first_image": false,
        "desktop_content_position": "middle-center",
        "show_text_box": true,
        "desktop_content_alignment": "center",
        "color_scheme": "background-1",
        "mobile_content_alignment": "center",
        "stack_images_on_mobile": true,
        "show_text_below": true
      }
    },
    "16604612272b74cc1f": {
      "type": "rich-text",
      "blocks": {
        "54437000-d054-4043-9770-bbea39ee8e54": {
          "type": "heading",
          "settings": {
            "heading": "<h2>How to deal with noise sensitivity<\/h2>",
            "heading_size": "h1"
          }
        },
        "1660461227266cb95c-1": {
          "type": "text",
          "settings": {
            "text": "<p>Whether you suffer from phonophobia, misophonia, hyperacusis, or a general anxiety caused by loud noises, you don’t need to suffer forever. <\/p><p>You may not be able to completely cure your noise anxiety, but the good news is that there are lots of ways to get relief from sounds that cause anxiety. Let’s take a look at some of the key things you can do to help you cope with auditory anxiety, whatever the cause.<\/p>",
            "description_padding": 32
          }
        },
        "74435391-32a2-4db6-bb7c-0731134fd5d6": {
          "type": "heading",
          "settings": {
            "heading": "<h3>1. Try not to avoid loud places<\/h3>",
            "heading_size": "h2"
          }
        },
        "23ff2b7b-1624-42e0-a9a2-698c90bbe716": {
          "type": "text",
          "settings": {
            "text": "<p>Yes, you read that right. It might sound counterintuitive, but hear us out. <\/p><p><a href=\"https:\/\/www.loopearplugs.com\/pages\/noise-sensitivity\"><span style=\"text-decoration:underline\">Noise sensitivity issues<\/span><\/a> often elicit a fight or flight response, so one of the most common effects is for people to simply avoid loud places altogether. <\/p><p>However, not only can this have a serious impact on their quality of life, it can actually make the problem even worse when they inevitably do encounter loud noises.<\/p><p>So, it’s important to try to live life as normally as possible and find ways to mitigate and treat your anxiety rather than completely avoid loud environments.<\/p>",
            "description_padding": 32
          }
        },
        "8a45f1c4-319d-4d8e-8f6a-882a3d9a3557": {
          "type": "heading",
          "settings": {
            "heading": "<h2>2. Get more comfortable in loud environments<\/h2>",
            "heading_size": "h2"
          }
        },
        "1f2a8760-5d69-406d-9bfc-b25c4165199b": {
          "type": "text",
          "settings": {
            "text": "<p>While it’s important not to avoid loud environments all together, earplugs are a simple way for anyone suffering from a form of noise sensitivity anxiety to live a more comfortable life. <\/p><p>If you feel overwhelmed by loud environments, earplugs can reduce the intensity so you won’t have to avoid social situations, and may also help to reduce anticipatory anxiety. Different earplugs are suited to different situations, so <a href=\"https:\/\/www.loopearplugs.com\/pages\/quiz\"><span style=\"text-decoration:underline\">choosing the right earplugs<\/span><\/a> is important.<\/p><p>Earplugs are affordable, small, and effective. It’s important not to become overly reliant on earplugs or completely drown out sounds, as this may make you more sensitive to them over time. However, they can help to filter out background noise and allow you to focus on your work or on conversations when you’re somewhere loud.<\/p><p>What’s more, just carrying them in your pocket can greatly reduce the risk of being caught out unexpectedly, and many people find that this enables them to live without the fear of loud noises. <\/p>",
            "description_padding": 32
          }
        }
      },
      "block_order": [
        "54437000-d054-4043-9770-bbea39ee8e54",
        "1660461227266cb95c-1",
        "74435391-32a2-4db6-bb7c-0731134fd5d6",
        "23ff2b7b-1624-42e0-a9a2-698c90bbe716",
        "8a45f1c4-319d-4d8e-8f6a-882a3d9a3557",
        "1f2a8760-5d69-406d-9bfc-b25c4165199b"
      ],
      "settings": {
        "desktop_content_position": "center",
        "content_alignment": "left",
        "color_scheme": "background-1",
        "full_width": true,
        "decription_max_width": 100,
        "padding_top": 40,
        "padding_bottom": 44
      }
    },
    "3505fac2-e146-4081-8700-43ece3abb7f2": {
      "type": "loop-featured-products",
      "blocks": {
        "17833861-4766-47ad-989c-41d96321bf0d": {
          "type": "select",
          "settings": {
            "product": "engage"
          }
        },
        "585a260f-ef95-4ded-a1cc-f009acde6ccb": {
          "type": "select",
          "settings": {
            "product": "experience"
          }
        },
        "8da844d4-9928-4873-9d5c-0016490b3d5a": {
          "type": "select",
          "settings": {
            "product": "quiet"
          }
        }
      },
      "block_order": [
        "17833861-4766-47ad-989c-41d96321bf0d",
        "585a260f-ef95-4ded-a1cc-f009acde6ccb",
        "8da844d4-9928-4873-9d5c-0016490b3d5a"
      ],
      "settings": {
        "title": "Our earplugs for noise sensitivity",
        "heading_size": "h1",
        "description": "",
        "description_style": "body",
        "columns_desktop": 4,
        "full_width": false,
        "color_scheme": "background-1",
        "image_ratio": "adapt",
        "show_secondary_image": false,
        "show_rating": false,
        "columns_mobile": "1",
        "swipe_on_mobile": true,
        "padding_top": 44,
        "padding_bottom": 16
      }
    },
    "9f9a1dc1-de29-4705-bba6-98eb2b6b1e71": {
      "type": "rich-text",
      "blocks": {
        "f32a8001-5016-4ef3-9ecc-abd64a1c751c": {
          "type": "heading",
          "settings": {
            "heading": "<h3>3. Specialized hearing aids<\/h3>",
            "heading_size": "h2"
          }
        },
        "6adfc57c-fb37-4b69-b231-cce0feaf808e": {
          "type": "text",
          "settings": {
            "text": "<p>You may associate hearing aids with increased sound intensity, but some devices can actually benefit sufferers of noise sensitivity anxiety by emitting a calming sound, such as running water. <\/p><p>This is a type of sound therapy, and for some people, it can help to reduce feelings of panic that are triggered by hearing certain noises.<\/p><p>By wearing the hearing aids, they’re able to focus on the calming sound instead of the external noises and over time, their response to the external noise may lessen, enabling them to live their life without being crippled by noise anxiety.<\/p>",
            "description_padding": 32
          }
        },
        "a7d9441b-d707-4159-8c9f-bf9dcc32442c": {
          "type": "heading",
          "settings": {
            "heading": "<h3>4. Cognitive behavioral therapy<\/h3>",
            "heading_size": "h2"
          }
        },
        "25ffc2d0-2d41-44a5-8723-cb85ab221002": {
          "type": "text",
          "settings": {
            "text": "<p>For serious cases of noise sensitivity anxiety, cognitive behavioral therapy (CBT) can be highly effective.<\/p><p>CBT helps people to change their thought patterns, learning how to switch their thinking so negative thoughts are replaced with positive ones. Because our thoughts influence our emotions and reactions, that means people with noise anxiety can begin to see their trigger noises in a different light and react to them differently.<\/p><p>CBT should always be done under professional guidance and is not an instant fix, but as a noise sensitivity anxiety treatment, it can be life-changing for extreme sufferers of noise-related anxiety.<\/p>",
            "description_padding": 32
          }
        },
        "8aa4e043-e646-4a11-95ba-b760776f8385": {
          "type": "heading",
          "settings": {
            "heading": "<h3>5. Exposure therapy to reduce your stress response<\/h3>",
            "heading_size": "h2"
          }
        },
        "8e843d48-8887-4a80-9fc8-5f09319a45e6": {
          "type": "text",
          "settings": {
            "text": "<p>Exposure therapy, either with the help of a professional or simply by gradually exposing yourself to loud noises in a controlled way, can also help you respond less severely to loud situations. To expose yourself to noises, try the following steps:<\/p><ul><li><strong>Determine which sound or sounds you are most sensitive to. <\/strong>It could be a specific sound, such as a type of music, coughing, or banging, or it could simply be any noise over a certain volume.<\/li><li><strong>Record the noise<\/strong>, or find a recording of it online.<\/li><li><strong>Go somewhere comfortable<\/strong>, such as at home on your couch, and <strong>try to imagine the soun<\/strong>d. Try to familiarize yourself with it and notice if you feel anxiety. Use relaxation techniques if necessary.<\/li><li>Once you feel a little more comfortable with the sound, <strong>try listening to the recording of it at a low volume<\/strong>. It’s likely that you’ll feel anxious, so take it slowly.<\/li><li><strong>Practice relaxation techniques<\/strong> (such as meditation and breathing techniques) to manage your anxiety levels if they start to rise.<\/li><li><strong>Increase the volume<\/strong> of the recording as you become more used to it.<\/li><\/ul><p><strong>Repeat this at regular intervals<\/strong>, for example daily, or as often as you can manage. Over time, your response should start to become less intense.<\/p>",
            "description_padding": 32
          }
        }
      },
      "block_order": [
        "f32a8001-5016-4ef3-9ecc-abd64a1c751c",
        "6adfc57c-fb37-4b69-b231-cce0feaf808e",
        "a7d9441b-d707-4159-8c9f-bf9dcc32442c",
        "25ffc2d0-2d41-44a5-8723-cb85ab221002",
        "8aa4e043-e646-4a11-95ba-b760776f8385",
        "8e843d48-8887-4a80-9fc8-5f09319a45e6"
      ],
      "settings": {
        "desktop_content_position": "center",
        "content_alignment": "left",
        "color_scheme": "background-1",
        "full_width": true,
        "decription_max_width": 100,
        "padding_top": 44,
        "padding_bottom": 44
      }
    },
    "b5c2fa2c-a1d8-445e-afbe-d6cec1114e53": {
      "type": "image-banner",
      "blocks": {
        "56da1443-7a8f-492c-bcd5-77e5353b7424": {
          "type": "heading",
          "disabled": true,
          "settings": {
            "heading": "Image banner",
            "heading_size": "h1"
          }
        },
        "a27ab979-2e71-4a0a-88e8-89ff696bee54": {
          "type": "text",
          "disabled": true,
          "settings": {
            "text": "Give customers details about the banner image(s) or content on the template.",
            "richtext": "",
            "text_style": "body"
          }
        },
        "a4505437-6d34-4fcc-bee4-c53130db82ad": {
          "type": "buttons",
          "disabled": true,
          "settings": {
            "button_label_1": "Button label",
            "button_link_1": "",
            "button_style_secondary_1": false,
            "button_bgcolor_1": "",
            "button_txtcolor_1": "",
            "button_label_2": "Button label",
            "button_link_2": "",
            "button_style_secondary_2": false,
            "button_bgcolor_2": "",
            "button_txtcolor_2": "",
            "button_label_3": "Button label",
            "show_id": ""
          }
        }
      },
      "block_order": [
        "56da1443-7a8f-492c-bcd5-77e5353b7424",
        "a27ab979-2e71-4a0a-88e8-89ff696bee54",
        "a4505437-6d34-4fcc-bee4-c53130db82ad"
      ],
      "settings": {
        "image": "shopify:\/\/shop_images\/Therapy_Session.jpg",
        "lazyload": true,
        "image_overlay_opacity": 0,
        "image_height": "small",
        "margin_top": true,
        "adapt_height_first_image": false,
        "desktop_content_position": "middle-center",
        "show_text_box": true,
        "desktop_content_alignment": "center",
        "color_scheme": "background-1",
        "mobile_content_alignment": "center",
        "stack_images_on_mobile": true,
        "show_text_below": true
      }
    },
    "0da19394-b527-4484-ae9e-3e2285896184": {
      "type": "image-banner",
      "disabled": true,
      "blocks": {
        "11a254e7-5bdf-4314-809c-750597dd10d2": {
          "type": "heading",
          "disabled": true,
          "settings": {
            "heading": "Image banner",
            "heading_size": "h1"
          }
        },
        "356bfe9f-f808-4c18-b5c6-81584c984e91": {
          "type": "text",
          "disabled": true,
          "settings": {
            "text": "Give customers details about the banner image(s) or content on the template.",
            "richtext": "",
            "text_style": "body"
          }
        },
        "54925a19-2472-4662-b339-39e3520ed82b": {
          "type": "buttons",
          "disabled": true,
          "settings": {
            "button_label_1": "Button label",
            "button_link_1": "",
            "button_style_secondary_1": false,
            "button_bgcolor_1": "",
            "button_txtcolor_1": "",
            "button_label_2": "Button label",
            "button_link_2": "",
            "button_style_secondary_2": false,
            "button_bgcolor_2": "",
            "button_txtcolor_2": "",
            "button_label_3": "Button label",
            "show_id": ""
          }
        }
      },
      "block_order": [
        "11a254e7-5bdf-4314-809c-750597dd10d2",
        "356bfe9f-f808-4c18-b5c6-81584c984e91",
        "54925a19-2472-4662-b339-39e3520ed82b"
      ],
      "settings": {
        "image": "shopify:\/\/shop_images\/earplugs-to-prevent-tinnitus_a38088f2-d95a-42e3-b780-b69f35f91af5.jpg",
        "lazyload": true,
        "image_overlay_opacity": 0,
        "image_height": "small",
        "margin_top": true,
        "adapt_height_first_image": false,
        "desktop_content_position": "middle-center",
        "show_text_box": true,
        "desktop_content_alignment": "center",
        "color_scheme": "background-1",
        "mobile_content_alignment": "center",
        "stack_images_on_mobile": true,
        "show_text_below": true
      }
    },
    "820555b6-a990-46e3-8524-cde208ce975c": {
      "type": "featured-product",
      "disabled": true,
      "blocks": {
        "template--15826134302916__820555b6-a990-46e3-8524-cde208ce975c-16752494005d4d9b91-0": {
          "type": "text",
          "settings": {
            "text": "{{ section.settings.product.vendor }}",
            "text_style": "uppercase"
          }
        },
        "template--15826134302916__820555b6-a990-46e3-8524-cde208ce975c-16752494005d4d9b91-1": {
          "type": "title",
          "settings": {
            "heading_size": "h1"
          }
        },
        "template--15826134302916__820555b6-a990-46e3-8524-cde208ce975c-16752494005d4d9b91-2": {
          "type": "text",
          "settings": {
            "text": "{{ section.settings.product.metafields.descriptors.subtitle.value }}",
            "text_style": "subtitle"
          }
        },
        "template--15826134302916__820555b6-a990-46e3-8524-cde208ce975c-16752494005d4d9b91-3": {
          "type": "price",
          "settings": {
          }
        },
        "template--15826134302916__820555b6-a990-46e3-8524-cde208ce975c-16752494005d4d9b91-4": {
          "type": "variant_picker",
          "settings": {
            "picker_type": "button"
          }
        },
        "template--15826134302916__820555b6-a990-46e3-8524-cde208ce975c-16752494005d4d9b91-5": {
          "type": "quantity_selector",
          "settings": {
          }
        },
        "template--15826134302916__820555b6-a990-46e3-8524-cde208ce975c-16752494005d4d9b91-6": {
          "type": "buy_buttons",
          "settings": {
            "show_dynamic_checkout": true
          }
        },
        "template--15826134302916__820555b6-a990-46e3-8524-cde208ce975c-16752494005d4d9b91-7": {
          "type": "share",
          "settings": {
            "share_label": "Share"
          }
        }
      },
      "block_order": [
        "template--15826134302916__820555b6-a990-46e3-8524-cde208ce975c-16752494005d4d9b91-0",
        "template--15826134302916__820555b6-a990-46e3-8524-cde208ce975c-16752494005d4d9b91-1",
        "template--15826134302916__820555b6-a990-46e3-8524-cde208ce975c-16752494005d4d9b91-2",
        "template--15826134302916__820555b6-a990-46e3-8524-cde208ce975c-16752494005d4d9b91-3",
        "template--15826134302916__820555b6-a990-46e3-8524-cde208ce975c-16752494005d4d9b91-4",
        "template--15826134302916__820555b6-a990-46e3-8524-cde208ce975c-16752494005d4d9b91-5",
        "template--15826134302916__820555b6-a990-46e3-8524-cde208ce975c-16752494005d4d9b91-6",
        "template--15826134302916__820555b6-a990-46e3-8524-cde208ce975c-16752494005d4d9b91-7"
      ],
      "settings": {
        "product": "quiet",
        "color_scheme": "#ffffff",
        "secondary_background": false,
        "hide_variants": false,
        "enable_video_looping": false,
        "padding_top": 36,
        "padding_bottom": 36
      }
    },
    "d1537d8c-2857-4fa6-ae59-fb97fb3b21a0": {
      "type": "rich-text",
      "blocks": {
        "3e7e9421-23aa-4498-ae75-eabce93a850f": {
          "type": "heading",
          "settings": {
            "heading": "<h3>6. Minimize stress<\/h3>",
            "heading_size": "h2"
          }
        },
        "41af495c-33da-4723-85b5-afd3ac147c12": {
          "type": "text",
          "settings": {
            "text": "<p>Do you ever find that your noise anxiety gets worse when you’ve had a broken night’s sleep, or you’ve got lots of deadlines at work? That’s because we’re more sensitive when we’re stressed, so we have lower tolerance levels. Noises that might not normally bother you can turn into sounds that cause anxiety. <\/p><p>You’ll probably find that you feel better and are better able to deal with loud places if you take steps to banish stress from your life – or at least, find ways to deal with it.<\/p><p>Some things you can do to relieve stress include:<\/p><ul><li><strong>Getting regular exercise:<\/strong> Being physically active will give you a boost of endorphins, the feel-good hormones that can reduce your stress levels and give you more energy.<\/li><li><strong>Get plenty of sleep: <\/strong>If you’re not getting enough sleep, everything seems more stressful and you may find that your anxiety worsens. Try to get a solid 8-9 hours of sleep per night, and practice <a href=\"https:\/\/www.loopearplugs.com\/blogs\/blog\/improving-sleep-hygiene\"><span style=\"text-decoration:underline\">good sleep hygiene<\/span><\/a> to ensure it’s good quality sleep, too. <\/li><li><strong>Spend time doing things you love:<\/strong> Whatever your hobby, from D&D to watching Drag Race, make sure you spend time every week doing something that brings you joy. <\/li><li><strong>Journal: <\/strong>Writing in a journal helps you to work through all of your thoughts and feelings. It can be a great outlet if you’re feeling stressed, rather than keeping all of your feelings inside. It can also help you to release your anxieties – if you write them down, it gives them a permanent home, signaling to your brain that it doesn’t need to focus on them so much.<\/li><li><strong>Deep breathing: <\/strong>Learning deep breathing techniques is a great way not only to become less stressed, but also to calm yourself down if you find yourself becoming anxious or panicked when exposed to noise.<\/li><\/ul>",
            "description_padding": 32
          }
        },
        "1daabdd0-ca75-4c26-8e36-a24dcc37bbf6": {
          "type": "heading",
          "settings": {
            "heading": "<h3>7. Find support<\/h3>",
            "heading_size": "h2"
          }
        },
        "71638c81-882f-4c68-b07f-dbd9c22d2be5": {
          "type": "text",
          "settings": {
            "text": "<p>You don’t need to deal with anxiety from noise alone – and you’re definitely not the only person to experience it, even though it can feel that way sometimes. <\/p><p>Speak up to your friends and family about how you’re feeling. Whether they also suffer from noise anxiety or not, just talking to them may help to lessen your anxious feelings. It also gives you an opportunity to discuss whether there’s anything they can do to help.<\/p><p>There are also plenty of great online communities where you’re sure to find like minded people. You’ll find groups for each of the noise anxiety-related conditions, like the <a href=\"https:\/\/www.meetup.com\/sound-sensitivity\/\"><span style=\"text-decoration:underline\">UK Misophonia Support Group<\/span><\/a> on Meetup and the <a href=\"https:\/\/www.facebook.com\/groups\/Hyperacusis\/\"><span style=\"text-decoration:underline\">Support for Pain Hyperacusis Facebook group<\/span><\/a>.<\/p>",
            "description_padding": 32
          }
        },
        "9244111c-0201-48e8-aef4-c78b18c14326": {
          "type": "heading",
          "settings": {
            "heading": "<h3>8. Speak to a medical professional<\/h3>",
            "heading_size": "h2"
          }
        },
        "b20edebd-2d3e-4cb4-b09e-ad864c5c2c34": {
          "type": "text",
          "settings": {
            "text": "<p>Often, noise anxiety coexists alongside other conditions, such as:<\/p><ul><li>General anxiety disorder<\/li><li>Depression<\/li><li>ADHD<\/li><li>Post-traumatic stress disorder (PTSD)<\/li><li>Autism<\/li><li>Obsessive-compulsive disorder (OCD)<\/li><\/ul><p>If you have another condition that isn’t being treated, it may be making your sensitivity to noise anxiety even worse. Seeking treatment for these other conditions may help to relieve some of the anxiety you experience when faced with loud or annoying noises.<\/p><p>If you’re scared of loud noises or have anxiety with loud noises, it’s a good idea to speak to your doctor. They’ll assess which form of noise anxiety you’re suffering from, and whether there are any other conditions that also need to be addressed, and they’ll advise you on the best noise sensitivity anxiety treatments for your situation.<\/p>",
            "description_padding": 32
          }
        }
      },
      "block_order": [
        "3e7e9421-23aa-4498-ae75-eabce93a850f",
        "41af495c-33da-4723-85b5-afd3ac147c12",
        "1daabdd0-ca75-4c26-8e36-a24dcc37bbf6",
        "71638c81-882f-4c68-b07f-dbd9c22d2be5",
        "9244111c-0201-48e8-aef4-c78b18c14326",
        "b20edebd-2d3e-4cb4-b09e-ad864c5c2c34"
      ],
      "settings": {
        "desktop_content_position": "center",
        "content_alignment": "left",
        "color_scheme": "background-1",
        "full_width": true,
        "decription_max_width": 100,
        "padding_top": 44,
        "padding_bottom": 44
      }
    },
    "6d4c2fb5-44b7-4c64-81f0-922af5635782": {
      "type": "image-with-text",
      "disabled": true,
      "blocks": {
        "1386a1a4-aef0-4a18-8ef8-ea0462fb9c7a": {
          "type": "heading",
          "settings": {
            "heading": "Is there a cure for tinnitus?",
            "heading_size": "h2"
          }
        },
        "template--15758497120452__6d4c2fb5-44b7-4c64-81f0-922af5635782-16668720159e416163-1": {
          "type": "text",
          "settings": {
            "text": "<p>If your tinnitus is caused by an underlying health condition, then addressing the cause will either stop the tinnitus completely or reduce its impact. <\/p><p>If your tinnitus is due to your ears being blocked with ear wax, for example, then using ear drops or having the earwax removed by an audiologist is likely to stop your symptoms.<\/p><p>If there’s no clear cause of your tinnitus, then it may be more about managing your symptoms rather than curing your ringing ears entirely. Some treatments for tinnitus include:<\/p>",
            "text_style": "body"
          }
        }
      },
      "block_order": [
        "1386a1a4-aef0-4a18-8ef8-ea0462fb9c7a",
        "template--15758497120452__6d4c2fb5-44b7-4c64-81f0-922af5635782-16668720159e416163-1"
      ],
      "settings": {
        "image": "shopify:\/\/shop_images\/earplugs-for-studying-DT.jpg",
        "height": "adapt",
        "desktop_image_width": "medium",
        "image_property": "cover",
        "layout": "image_first",
        "desktop_content_position": "top",
        "desktop_content_alignment": "left",
        "content_layout": "no-overlap",
        "color_scheme": "background-1",
        "mobile_content_alignment": "left",
        "padding_top": 44,
        "padding_bottom": 44
      }
    },
    "af390d07-1718-439f-8200-0f2218d8afe9": {
      "type": "rich-text",
      "blocks": {
        "79abc139-bb37-40fa-8d06-83619dcc23ac": {
          "type": "heading",
          "settings": {
            "heading": "<h2>Overcoming noise anxiety<\/h2>",
            "heading_size": "h1"
          }
        },
        "b4ecbf04-e53d-4563-a498-09502e87b0ff": {
          "type": "text",
          "settings": {
            "text": "<p>Anxiety caused by loud noises can have a huge impact on your life. But it’s important to remember that, with time and patience, there are ways you can minimize the effects it has on your day to day life. <\/p><p>From seeking the support of others to trying sound therapy, it’s a case of figuring out which treatment best works for you to help you lead a life free from anxiety.<\/p>",
            "description_padding": 32
          }
        }
      },
      "block_order": [
        "79abc139-bb37-40fa-8d06-83619dcc23ac",
        "b4ecbf04-e53d-4563-a498-09502e87b0ff"
      ],
      "settings": {
        "desktop_content_position": "center",
        "content_alignment": "left",
        "color_scheme": "background-1",
        "full_width": true,
        "decription_max_width": 100,
        "padding_top": 44,
        "padding_bottom": 44
      }
    },
    "3c067c96-000a-4dfc-9716-2870ba743bb2": {
      "type": "rich-text",
      "disabled": true,
      "blocks": {
        "template--15787235770564__3c067c96-000a-4dfc-9716-2870ba743bb2-166997577179d60747-0": {
          "type": "heading",
          "settings": {
            "heading": "<h3>2. Reducing the volume<\/h3>",
            "heading_size": "h2"
          }
        },
        "template--15787235770564__3c067c96-000a-4dfc-9716-2870ba743bb2-166997577179d60747-1": {
          "type": "text",
          "settings": {
            "text": "<p>As well as wearing earplugs, it’s important to be mindful of the volume at which you’re listening to music. Although listening to music on a daily basis might not seem like a problem, it’s something that most of us should be taking more seriously. Most people listen to music through their headphones or earbuds at 75 to 105 decibels. It takes just 8 hours of exposures to sound at 80 decibels without ear protection to cause damage.<\/p><p><strong>Kathleen Wallace<\/strong> explains:<\/p><p><em>“There is a lot of other noise that we are exposing ourselves to. It’s all self-inflicted. So if you are listening to music or podcasts or you’re watching TV, you have to think about what volume you’re listening at.”<\/em><\/p><p>She further explains:<\/p><p><em>“If you’re at a restaurant or some sort of situation where you don’t have your earplugs with you, I’d recommend downloading a sound level meter app where you can actually see how loud is this environment and you can make an educated decision about ‘do I want to stay in this environment?’, ‘how long can I stay in there and be safe?’ or ‘is there a quiet part I can move to, away from the kitchen or the bar?’.”<\/em><\/p>",
            "description_padding": 32
          }
        },
        "15446348-0259-43eb-a49e-b585689bff56": {
          "type": "heading",
          "settings": {
            "heading": "<h3>3. Improving your cardiovascular health<\/h3>",
            "heading_size": "h2"
          }
        },
        "501ea00e-b2a0-43a0-8819-38d57a54c532": {
          "type": "text",
          "settings": {
            "text": "<p>As mentioned already, certain conditions that affect your cardiovascular health can cause tinnitus, or make the ringing in your ears worse. <\/p><p>Maintaining good levels of cardio fitness, reducing your blood pressure and keeping your cholesterol at a healthy level may all help to prevent tinnitus.<\/p>",
            "description_padding": 32
          }
        }
      },
      "block_order": [
        "template--15787235770564__3c067c96-000a-4dfc-9716-2870ba743bb2-166997577179d60747-0",
        "template--15787235770564__3c067c96-000a-4dfc-9716-2870ba743bb2-166997577179d60747-1",
        "15446348-0259-43eb-a49e-b585689bff56",
        "501ea00e-b2a0-43a0-8819-38d57a54c532"
      ],
      "settings": {
        "desktop_content_position": "center",
        "content_alignment": "left",
        "color_scheme": "background-1",
        "full_width": true,
        "decription_max_width": 100,
        "padding_top": 44,
        "padding_bottom": 44
      }
    },
    "166046188908e08637": {
      "type": "rich-text",
      "disabled": true,
      "blocks": {
        "f82e4b6f-b5fc-4597-9b9f-eeb39509ad13": {
          "type": "heading",
          "settings": {
            "heading": "Manage your tinnitus",
            "heading_size": "h1"
          }
        },
        "213366c8-65ac-45dc-bba6-85e575252463": {
          "type": "text",
          "settings": {
            "text": "<p>Tinnitus can be difficult to live with, but there are ways to deal with it. Not all causes of tinnitus are preventable, but you can reduce your risk of developing it by protecting yourself from loud noises and hearing loss through the use of earplugs. You can also manage your symptoms through a variety of techniques including sound therapy, self care and addressing your hearing loss, all of which can help you to stay on top of the ringing in your ears and fully live your life, distraction-free.<\/p>",
            "description_padding": 32
          }
        }
      },
      "block_order": [
        "f82e4b6f-b5fc-4597-9b9f-eeb39509ad13",
        "213366c8-65ac-45dc-bba6-85e575252463"
      ],
      "settings": {
        "desktop_content_position": "center",
        "content_alignment": "left",
        "color_scheme": "background-1",
        "full_width": true,
        "decription_max_width": 100,
        "padding_top": 44,
        "padding_bottom": 44
      }
    },
    "165812615354029ad8": {
      "type": "loop-article-cta-button",
      "blocks": {
        "165812615340e78fbe-0": {
          "type": "button",
          "settings": {
            "button_label": "Find your Loops",
            "button_link": "shopify:\/\/collections\/all",
            "button_bgcolor_1": "#766294",
            "button_txtcolor_1": "",
            "button_style_secondary": false,
            "button_label_2": "",
            "button_link_2": "",
            "button_bgcolor_2": "#000000",
            "button_txtcolor_2": "",
            "button_style_secondary_2": false
          }
        }
      },
      "block_order": [
        "165812615340e78fbe-0"
      ],
      "settings": {
        "desktop_content_position": "center",
        "content_alignment": "center",
        "color_scheme": "#ffffff",
        "full_width": true,
        "padding_top": 44,
        "padding_bottom": 44
      }
    },
    "471e8632-50ea-4753-91ec-04de7755365c": {
      "type": "loop-featured-article",
      "blocks": {
        "535e670a-5009-4f44-906a-6eed6ff2ed9d": {
          "type": "select",
          "settings": {
            "article": "blog\/how-to-overcome-phonophobia"
          }
        },
        "3c556024-8341-45c0-9438-ee77ca8cce9a": {
          "type": "select",
          "settings": {
            "article": "blog\/are-misophonia-and-adhd-connected"
          }
        },
        "5e43164b-1bee-4a89-ad00-cfa566f35f0f": {
          "type": "select",
          "settings": {
            "article": "blog\/top-9-brilliant-misophonia-podcasts-to-listen-to"
          }
        }
      },
      "block_order": [
        "535e670a-5009-4f44-906a-6eed6ff2ed9d",
        "3c556024-8341-45c0-9438-ee77ca8cce9a",
        "5e43164b-1bee-4a89-ad00-cfa566f35f0f"
      ],
      "settings": {
        "columns_size": 3,
        "padding_top": 44,
        "padding_bottom": 44
      }
    },
    "1656053545f8bd8b7c": {
      "type": "loop-article-footer",
      "settings": {
        "color_scheme": "#ffffff"
      }
    }
  },
  "order": [
    "main",
    "16559742803aaa6577",
    "1658122483d764eac3",
    "206550a5-73db-4a85-bf30-dc6c1c292d48",
    "c1914074-e112-47ac-8be5-71e50691e7b4",
    "16581501774a32acf8",
    "16604607234acd9044",
    "fd43e1f8-2931-404c-b7b9-2f56c8f3afbc",
    "16604612272b74cc1f",
    "3505fac2-e146-4081-8700-43ece3abb7f2",
    "9f9a1dc1-de29-4705-bba6-98eb2b6b1e71",
    "b5c2fa2c-a1d8-445e-afbe-d6cec1114e53",
    "0da19394-b527-4484-ae9e-3e2285896184",
    "820555b6-a990-46e3-8524-cde208ce975c",
    "d1537d8c-2857-4fa6-ae59-fb97fb3b21a0",
    "6d4c2fb5-44b7-4c64-81f0-922af5635782",
    "af390d07-1718-439f-8200-0f2218d8afe9",
    "3c067c96-000a-4dfc-9716-2870ba743bb2",
    "166046188908e08637",
    "165812615354029ad8",
    "471e8632-50ea-4753-91ec-04de7755365c",
    "1656053545f8bd8b7c"
  ]
}
