{
  "sections": {
    "724be438-77a4-40d1-8c81-37274ed60ad4": {
      "type": "collection-filters",
      "blocks": {
        "0adb3e14-61ad-4516-b024-3df42d49b0ce": {
          "type": "filter",
          "settings": {
            "label": "I want to be in my bubble",
            "value": "27db"
          }
        },
        "145d8537-ed86-4002-a65a-43c8d3a8b84f": {
          "type": "filter",
          "settings": {
            "label": "I want to hear everything, just less loud",
            "value": "18db"
          }
        },
        "bd4b6e2c-ccdc-441a-9f30-bac8728cc272": {
          "type": "filter",
          "settings": {
            "label": "I want to reduce background noise, while keeping my speech clear",
            "value": "16db"
          }
        }
      },
      "block_order": [
        "0adb3e14-61ad-4516-b024-3df42d49b0ce",
        "145d8537-ed86-4002-a65a-43c8d3a8b84f",
        "bd4b6e2c-ccdc-441a-9f30-bac8728cc272"
      ],
      "settings": {
        "title": "How do you want to hear the world?"
      }
    },
    "851601bc-6b33-40b0-b528-439ef61462e7": {
      "type": "loop-segmented-collections",
      "blocks": {
        "ebc11f7f-255f-4648-a274-a69a2e17d2e9": {
          "type": "collection",
          "settings": {
            "collection": "earplugs",
            "heading": "Earplugs",
            "link_url": "",
            "link_label": "",
            "new_enabled": false
          }
        },
        "818c6939-2f95-4f9a-a773-4caaf56dd91a": {
          "type": "collection",
          "settings": {
            "collection": "solstice-collection",
            "heading": "Solstice Collection",
            "link_url": "shopify:\/\/pages\/solstice",
            "link_label": "Learn more",
            "new_enabled": true
          }
        },
        "727f3e93-b8f1-4c7e-894f-42b5c264877e": {
          "type": "collection",
          "disabled": true,
          "settings": {
            "collection": "iridescent-collection",
            "heading": "Iridescent Collection",
            "link_url": "shopify:\/\/pages\/iridescent",
            "link_label": "Learn more",
            "new_enabled": true
          }
        },
        "512e67a4-1155-4546-bea2-9a6e214ebd72": {
          "type": "collection",
          "settings": {
            "collection": "loop-yours-accessories",
            "heading": "Accessories",
            "link_url": "",
            "link_label": "",
            "new_enabled": false
          }
        }
      },
      "block_order": [
        "ebc11f7f-255f-4648-a274-a69a2e17d2e9",
        "818c6939-2f95-4f9a-a773-4caaf56dd91a",
        "727f3e93-b8f1-4c7e-894f-42b5c264877e",
        "512e67a4-1155-4546-bea2-9a6e214ebd72"
      ],
      "settings": {
        "padding_top": 36,
        "padding_bottom": 36
      }
    },
    "banner": {
      "type": "main-collection-banner",
      "disabled": true,
      "settings": {
        "show_collection_description": false,
        "show_collection_image": false,
        "color_scheme": "background-1"
      }
    },
    "product-grid": {
      "type": "main-collection-product-grid",
      "disabled": true,
      "settings": {
        "products_per_page": 16,
        "columns_desktop": 4,
        "image_ratio": "square",
        "show_secondary_image": true,
        "show_vendor": false,
        "show_rating": true,
        "enable_quick_add": false,
        "enable_filtering": true,
        "filter_type": "horizontal",
        "enable_sorting": true,
        "columns_mobile": "2",
        "padding_top": 36,
        "padding_bottom": 36
      }
    }
  },
  "order": [
    "724be438-77a4-40d1-8c81-37274ed60ad4",
    "851601bc-6b33-40b0-b528-439ef61462e7",
    "banner",
    "product-grid"
  ]
}
