{
  "sections": {
    "banner": {
      "type": "main-collection-banner-cpb",
      "settings": {
        "show_collection_description": true,
        "show_collection_image": false,
        "color_scheme": "background-1"
      }
    },
    "1370e1df-9a35-4ec8-a3e6-3f25f07847b3": {
      "type": "slider-cpb",
      "blocks": {
        "5da01839-dfff-43b4-813b-04a6658367d5": {
          "type": "slide",
          "settings": {
            "title": "クレ・ド・ポー ボーテ 2023\nホリデーコレクション",
            "image": "shopify:\/\/shop_images\/offer_holiday2023_pc.jpg",
            "image_sp": "shopify:\/\/shop_images\/offer_holiday2023_sp.jpg",
            "link": "",
            "is_title_white": true,
            "is_text_right": false
          }
        },
        "c5f49fbb-3665-4823-9f17-172b0219bd14": {
          "type": "slide",
          "settings": {
            "title": "自らを鍛える\n進化した、4D*ハリ美容液。\n＊4Dとは美しいフェイスラインの肌へ導くことに加えて、\n肌表面を整え見た目からもハリのある印象の肌に導く\n独自の考え方のことです。",
            "image": "shopify:\/\/shop_images\/offer_firming-serum-supreme_23aw_pc.jpg",
            "image_sp": "shopify:\/\/shop_images\/offer_firming-serum-supreme_23aw_sp.jpg",
            "link": "shopify:\/\/products\/cle-de-peau-beaute-ceramula-fermisan-s-n-2023-09-21",
            "is_title_white": false,
            "is_text_right": false
          }
        }
      },
      "block_order": [
        "5da01839-dfff-43b4-813b-04a6658367d5",
        "c5f49fbb-3665-4823-9f17-172b0219bd14"
      ],
      "settings": {
      }
    },
    "product-grid": {
      "type": "main-collection-product-grid-cpb",
      "settings": {
        "products_per_page": 16,
        "columns_desktop": 4,
        "image_ratio": "adapt",
        "image_shape": "default",
        "show_secondary_image": false,
        "show_vendor": false,
        "show_rating": false,
        "enable_quick_add": false,
        "enable_filtering": true,
        "filter_type": "horizontal",
        "enable_sorting": true,
        "columns_mobile": "2",
        "padding_top": 36,
        "padding_bottom": 36,
        "products_to_show": 4,
        "enable_desktop_slider": true,
        "swipe_on_mobile": true
      }
    }
  },
  "order": [
    "banner",
    "1370e1df-9a35-4ec8-a3e6-3f25f07847b3",
    "product-grid"
  ]
}
