{
  "sections": {
    "main": {
      "type": "main-page",
      "disabled": true,
      "settings": {
        "padding_top": 28,
        "padding_bottom": 28
      }
    },
    "995effe8-0365-4b37-afc9-0c1f4e7b3965": {
      "type": "loop-slideshow",
      "blocks": {
        "template--15744165773508__995effe8-0365-4b37-afc9-0c1f4e7b3965-1665399704261acd45-0": {
          "type": "slide",
          "settings": {
            "image": "shopify:\/\/shop_images\/Hero_Img_desktop_1.png",
            "image_3": "shopify:\/\/shop_images\/Hero_Img_mobile_1_cad46cfb-ad87-4097-9541-f15e8dbd795b.png",
            "heading": "A NEW WAVE OF LOOPS INCOMING",
            "heading_size": "loop-xl",
            "subheading": "You told us about your biggest earplug woes, and we listened. We’ve been developing something special behind the scenes.    Sign up to our newsletter to get notified when they drop.",
            "subhead_color": "#252427",
            "button_label": "",
            "link": "",
            "button_style_secondary": false,
            "button2_label": "",
            "button2_link": "",
            "button2_style_secondary": false,
            "show_newsletter_form": true,
            "box_align": "middle-left",
            "show_text_box": true,
            "text_alignment": "left",
            "image_overlay_opacity": 0,
            "color_scheme": "background-2",
            "text_alignment_mobile": "center"
          }
        }
      },
      "block_order": [
        "template--15744165773508__995effe8-0365-4b37-afc9-0c1f4e7b3965-1665399704261acd45-0"
      ],
      "settings": {
        "layout": "full_bleed",
        "slide_height": "large",
        "slider_visual": "counter",
        "auto_rotate": false,
        "change_slides_speed": 5,
        "heading_max_width": 100,
        "subheading_max_width": 100,
        "show_text_below": true,
        "accessibility_info": "Slideshow about our brand"
      }
    },
    "ac011508-9757-495b-90e4-01511bd103da": {
      "type": "loop-slideshow",
      "blocks": {
        "template--15744165773508__ac011508-9757-495b-90e4-01511bd103da-16654001327c6a522b-0": {
          "type": "slide",
          "settings": {
            "image": "shopify:\/\/shop_images\/Image_desktop_1.png",
            "image_3": "shopify:\/\/shop_images\/Image_mobile_1.png",
            "heading": "",
            "heading_size": "h1",
            "subheading": "",
            "subhead_color": "#252427",
            "button_label": "",
            "link": "",
            "button_style_secondary": false,
            "button2_label": "",
            "button2_link": "",
            "button2_style_secondary": false,
            "show_newsletter_form": false,
            "box_align": "middle-center",
            "show_text_box": false,
            "text_alignment": "center",
            "image_overlay_opacity": 0,
            "color_scheme": "background-1",
            "text_alignment_mobile": "center"
          }
        },
        "template--15744165773508__ac011508-9757-495b-90e4-01511bd103da-16654001327c6a522b-1": {
          "type": "slide",
          "settings": {
            "image": "shopify:\/\/shop_images\/Image_desktop_2.png",
            "image_3": "shopify:\/\/shop_images\/Image_mobile_2.png",
            "heading": "",
            "heading_size": "h1",
            "subheading": "",
            "subhead_color": "#252427",
            "button_label": "",
            "link": "",
            "button_style_secondary": false,
            "button2_label": "",
            "button2_link": "",
            "button2_style_secondary": false,
            "show_newsletter_form": false,
            "box_align": "middle-center",
            "show_text_box": false,
            "text_alignment": "center",
            "image_overlay_opacity": 0,
            "color_scheme": "background-1",
            "text_alignment_mobile": "center"
          }
        },
        "badf531e-58fb-4555-aeb7-59a878d50643": {
          "type": "slide",
          "settings": {
            "image": "shopify:\/\/shop_images\/Image_desktop_3.png",
            "image_3": "shopify:\/\/shop_images\/Image_mobile_3.png",
            "heading": "",
            "heading_size": "h1",
            "subheading": "",
            "subhead_color": "#252427",
            "button_label": "",
            "link": "",
            "button_style_secondary": false,
            "button2_label": "",
            "button2_link": "",
            "button2_style_secondary": false,
            "show_newsletter_form": false,
            "box_align": "middle-center",
            "show_text_box": false,
            "text_alignment": "center",
            "image_overlay_opacity": 0,
            "color_scheme": "background-1",
            "text_alignment_mobile": "center"
          }
        }
      },
      "block_order": [
        "template--15744165773508__ac011508-9757-495b-90e4-01511bd103da-16654001327c6a522b-0",
        "template--15744165773508__ac011508-9757-495b-90e4-01511bd103da-16654001327c6a522b-1",
        "badf531e-58fb-4555-aeb7-59a878d50643"
      ],
      "settings": {
        "layout": "full_bleed",
        "slide_height": "large",
        "slider_visual": "dots",
        "auto_rotate": false,
        "change_slides_speed": 5,
        "heading_max_width": 86,
        "subheading_max_width": 82,
        "show_text_below": false,
        "accessibility_info": "Slideshow about our brand"
      }
    },
    "a1f51ad9-83ca-4a03-afc0-abdd515b7019": {
      "type": "rich-text",
      "blocks": {
        "template--15744165773508__a1f51ad9-83ca-4a03-afc0-abdd515b7019-1665401185c3569964-0": {
          "type": "heading",
          "settings": {
            "heading": "Follow us on Instagram",
            "heading_size": "h1"
          }
        }
      },
      "block_order": [
        "template--15744165773508__a1f51ad9-83ca-4a03-afc0-abdd515b7019-1665401185c3569964-0"
      ],
      "settings": {
        "desktop_content_position": "center",
        "content_alignment": "center",
        "color_scheme": "background-1",
        "full_width": true,
        "decription_max_width": 100,
        "padding_top": 88,
        "padding_bottom": 0
      }
    },
    "eeb56604-0ece-4c20-b1c6-06e4f672d26b": {
      "type": "instafeed",
      "settings": {
        "heading_size": 20,
        "feed_width": 100,
        "html_area": ""
      }
    },
    "5b188514-425d-423f-af34-0ac7894840ae": {
      "type": "rich-text",
      "blocks": {
        "template--15744165773508__5b188514-425d-423f-af34-0ac7894840ae-16654012509b4f1489-2": {
          "type": "button",
          "settings": {
            "button_label": "Follow Loop",
            "button_link": "https:\/\/www.instagram.com\/loopearplugs\/",
            "button_bgcolor_1": "",
            "button_txtcolor_1": "",
            "button_style_secondary": false,
            "button_label_2": "",
            "button_link_2": "",
            "button_bgcolor_2": "",
            "button_txtcolor_2": "",
            "button_style_secondary_2": false,
            "button_padding": 0
          }
        }
      },
      "block_order": [
        "template--15744165773508__5b188514-425d-423f-af34-0ac7894840ae-16654012509b4f1489-2"
      ],
      "settings": {
        "desktop_content_position": "center",
        "content_alignment": "center",
        "color_scheme": "background-1",
        "full_width": true,
        "decription_max_width": 100,
        "padding_top": 0,
        "padding_bottom": 88
      }
    },
    "663676eb-4d77-45db-a6c8-969f387498f3": {
      "type": "custom-liquid",
      "settings": {
        "custom_liquid": "<style>\n@media screen and (max-width: 749px) {\nslideshow-component {\n  max-height: 1090px;\n}\n}\n<\/style>",
        "color_scheme": "background-1",
        "padding_top": 0,
        "padding_bottom": 0
      }
    }
  },
  "order": [
    "main",
    "995effe8-0365-4b37-afc9-0c1f4e7b3965",
    "ac011508-9757-495b-90e4-01511bd103da",
    "a1f51ad9-83ca-4a03-afc0-abdd515b7019",
    "eeb56604-0ece-4c20-b1c6-06e4f672d26b",
    "5b188514-425d-423f-af34-0ac7894840ae",
    "663676eb-4d77-45db-a6c8-969f387498f3"
  ]
}