{
  "sections": {
    "main": {
      "type": "main-page",
      "disabled": true,
      "settings": {
        "padding_top": 28,
        "padding_bottom": 28
      }
    },
    "1645786349bb92c16e": {
      "type": "image-banner",
      "settings": {
        "image": "shopify:\/\/shop_images\/LP_Nightlife_Desktop_Lifestyle_65b053b3-5a8c-4faf-aedc-6003a90badd0.jpg",
        "image_3": "shopify:\/\/shop_images\/LP_Nightlife_Desktop_Lifestyle_65b053b3-5a8c-4faf-aedc-6003a90badd0.jpg",
        "lazyload": true,
        "image_overlay_opacity": 0,
        "image_height": "medium",
        "margin_top": true,
        "adapt_height_first_image": false,
        "desktop_content_position": "middle-center",
        "show_text_box": false,
        "desktop_content_alignment": "center",
        "color_scheme": "#fff",
        "mobile_content_alignment": "center",
        "stack_images_on_mobile": true,
        "show_text_below": false
      }
    },
    "16457863188a1c84d3": {
      "type": "rich-text",
      "blocks": {
        "16457863189f0cd477-0": {
          "type": "heading",
          "settings": {
            "heading": "Earplugs for concerts",
            "heading_size": "h0"
          }
        },
        "16457863189f0cd477-1": {
          "type": "text",
          "settings": {
            "text": "<p>87,649 people held their breath. <\/p><p>The lights were low. The tension of anticipation lingered in the air. Every single person was held in suspense. So many people in one place, but it was so quiet. The guitarist struck the first chord. The bass’s groans reverberated throughout the arena. The lights flashed. And the frontman began to sing. You just can’t beat a concert. The excitement of seeing your favorite artist. The bliss of hearing music you just love. The  mind-blowing power of music to bring so many of us together from all walks of life. It’s a beautiful thing. <\/p><p>But being at around 100dB, <strong>a concert can pose a problem for your hearing<\/strong>. <\/p>",
            "description_padding": 32
          }
        }
      },
      "block_order": [
        "16457863189f0cd477-0",
        "16457863189f0cd477-1"
      ],
      "settings": {
        "desktop_content_position": "center",
        "content_alignment": "center",
        "color_scheme": "#fff",
        "full_width": true,
        "decription_max_width": 100,
        "padding_top": 44,
        "padding_bottom": 44
      }
    },
    "a509a09c-1018-4eb2-b12f-0f9203475dc6": {
      "type": "image-banner",
      "disabled": true,
      "settings": {
        "image": "shopify:\/\/shop_images\/decibels-duration-hearing_1c84d0c9-3c92-457e-9ff2-079d2ec1b95c.webp",
        "lazyload": true,
        "image_overlay_opacity": 0,
        "image_height": "small",
        "margin_top": true,
        "adapt_height_first_image": true,
        "desktop_content_position": "middle-center",
        "show_text_box": true,
        "desktop_content_alignment": "center",
        "color_scheme": "background-1",
        "mobile_content_alignment": "center",
        "stack_images_on_mobile": true,
        "show_text_below": true
      }
    },
    "ad2c432f-2b38-47ef-9a80-5b253f5c2f56": {
      "type": "image-with-text",
      "settings": {
        "image": "shopify:\/\/shop_images\/decibels-duration-hearing.webp",
        "height": "adapt",
        "desktop_image_width": "large",
        "image_property": "cover",
        "layout": "image_first",
        "desktop_content_position": "top",
        "desktop_content_alignment": "center",
        "content_layout": "no-overlap",
        "color_scheme": "background-1",
        "mobile_content_alignment": "center",
        "padding_top": 44,
        "padding_bottom": 44
      }
    },
    "5baf8b65-901d-487b-b196-547e9054e979": {
      "type": "rich-text",
      "disabled": true,
      "blocks": {
        "template--15751466811588__5baf8b65-901d-487b-b196-547e9054e979-16660949476e004051-0": {
          "type": "heading",
          "settings": {
            "heading": "<p>Your ears are more fragile than you think<\/p>",
            "heading_size": "h1"
          }
        },
        "template--15751466811588__5baf8b65-901d-487b-b196-547e9054e979-16660949476e004051-1": {
          "type": "text",
          "settings": {
            "text": "<p>They have little hair follicles within them that turn soundwaves into electrical signals for your brain. When you’re exposed to loud noises from 70dB for a long time, these hairs can be damaged along with surrounding arteries. And they can’t come back from that. What happens then? Well, as a result 1.1 billion of us have a higher risk of hearing loss, according to the World Health Organization.<\/p><p>So what can we do? How do we protect our hearing at aconcert?<\/p>",
            "description_padding": 16
          }
        }
      },
      "block_order": [
        "template--15751466811588__5baf8b65-901d-487b-b196-547e9054e979-16660949476e004051-0",
        "template--15751466811588__5baf8b65-901d-487b-b196-547e9054e979-16660949476e004051-1"
      ],
      "settings": {
        "desktop_content_position": "center",
        "content_alignment": "center",
        "color_scheme": "background-1",
        "full_width": true,
        "decription_max_width": 100,
        "padding_top": 44,
        "padding_bottom": 44
      }
    },
    "3a7b4a7e-81fd-498c-a497-8968c3a75f79": {
      "type": "loop-article-img-txt",
      "blocks": {
        "template--15751466811588__3a7b4a7e-81fd-498c-a497-8968c3a75f79-166609539156a1f68a-0": {
          "type": "heading",
          "settings": {
            "heading": "Your ears are more fragile than you think",
            "heading_size": "h2"
          }
        },
        "template--15751466811588__3a7b4a7e-81fd-498c-a497-8968c3a75f79-166609539156a1f68a-1": {
          "type": "text",
          "settings": {
            "text": "<p>They have little hair follicles within them that turn soundwaves into electrical signals for your brain. When you’re exposed to loud noises from 70dB for a long time, these hairs can be damaged along with<br\/>surrounding arteries. <\/p><p>And they can’t come back from that. <\/p><p>What happens then? Well, as<br\/>a result 1.1 billion of us have a higher risk of hearing loss, according to the World Health Organization.<\/p><p>So what can we do? How do we protect our hearing at a concert?<\/p>",
            "text_style": "body"
          }
        }
      },
      "block_order": [
        "template--15751466811588__3a7b4a7e-81fd-498c-a497-8968c3a75f79-166609539156a1f68a-0",
        "template--15751466811588__3a7b4a7e-81fd-498c-a497-8968c3a75f79-166609539156a1f68a-1"
      ],
      "settings": {
        "image": "shopify:\/\/shop_images\/Use_Cases_Desk_4_4cfb1d99-86dc-4699-9201-e8df80f003ad.jpg",
        "video_url": "",
        "video-tag": "",
        "height": "adapt",
        "desktop_image_width": "medium",
        "layout": "image_first",
        "desktop_content_position": "top",
        "desktop_content_alignment": "left",
        "content_layout": "no-overlap",
        "color_scheme": "#ffffff",
        "mobile_content_alignment": "left",
        "padding_top": 44,
        "padding_bottom": 44
      }
    },
    "10843f6a-ac93-4a2b-8b91-b657d7ca3b90": {
      "type": "rich-text",
      "blocks": {
        "template--15751466811588__10843f6a-ac93-4a2b-8b91-b657d7ca3b90-1666095395e4ba86dc-0": {
          "type": "heading",
          "settings": {
            "heading": "Here’s why you can rest easy",
            "heading_size": "h1"
          }
        },
        "template--15751466811588__10843f6a-ac93-4a2b-8b91-b657d7ca3b90-1666095395e4ba86dc-1": {
          "type": "text",
          "settings": {
            "text": "<p><strong>The good news is that the right earplugs will do the trick. <\/strong><\/p><p>But what are the best earplugs for concerts? If you don't use the right ones, they can just muffle the sound and take away some of the joy from your concert experience. Plus, they can be uncomfortable and make you feel a little self-conscious. <\/p><p>We don’t want that, do we?<\/p><p>So that’s why we designed <a href=\"\/products\/experience\" target=\"_blank\" title=\"Experience\">Loop Experience<\/a><strong> <\/strong>–<strong> <\/strong>high-quality earplugs for concerts. <\/p><p>So you can comfortably listen to music without losing any sound quality. <\/p>",
            "description_padding": 32
          }
        }
      },
      "block_order": [
        "template--15751466811588__10843f6a-ac93-4a2b-8b91-b657d7ca3b90-1666095395e4ba86dc-0",
        "template--15751466811588__10843f6a-ac93-4a2b-8b91-b657d7ca3b90-1666095395e4ba86dc-1"
      ],
      "settings": {
        "desktop_content_position": "center",
        "content_alignment": "center",
        "color_scheme": "background-1",
        "full_width": true,
        "decription_max_width": 100,
        "padding_top": 44,
        "padding_bottom": 44
      }
    },
    "e81e33a8-46eb-4508-a15a-090a843d5c31": {
      "type": "loop-featured-products",
      "blocks": {
        "56f5ee8e-5e3b-4761-b813-f7dfabab4c00": {
          "type": "select",
          "settings": {
            "product": "experience-pro"
          }
        },
        "b94c0a31-16b1-4ad6-8413-ad472f5def5a": {
          "type": "select",
          "settings": {
            "product": "experience"
          }
        },
        "a864108d-1dd8-4d02-9604-9a8560204538": {
          "type": "select",
          "disabled": true,
          "settings": {
            "product": "experience-elements-edition"
          }
        },
        "3d50e3df-d7df-4a83-844e-f027f94c0899": {
          "type": "select",
          "disabled": true,
          "settings": {
            "product": ""
          }
        }
      },
      "block_order": [
        "56f5ee8e-5e3b-4761-b813-f7dfabab4c00",
        "b94c0a31-16b1-4ad6-8413-ad472f5def5a",
        "a864108d-1dd8-4d02-9604-9a8560204538",
        "3d50e3df-d7df-4a83-844e-f027f94c0899"
      ],
      "settings": {
        "title": "Our recommended Loops",
        "heading_size": "h1",
        "description": "",
        "description_style": "body",
        "columns_desktop": 3,
        "full_width": false,
        "color_scheme": "background-1",
        "image_ratio": "adapt",
        "show_secondary_image": false,
        "show_rating": false,
        "columns_mobile": "1",
        "swipe_on_mobile": true,
        "padding_top": 44,
        "padding_bottom": 44
      }
    },
    "9ed4066c-a046-482b-9f08-cfb717d13789": {
      "type": "collapsible-content",
      "blocks": {
        "template--15748392779972__9ed4066c-a046-482b-9f08-cfb717d13789-1666090534a02685d6-0": {
          "type": "collapsible_row",
          "settings": {
            "heading": "Sound good",
            "icon": "check_mark",
            "row_content": "<p>The acoustic resonator inside of<a href=\"https:\/\/www.loopearplugs.com\/products\/experience-pro\"> Loop Experience Pro<\/a> earplugs mimics how your ears work. This keeps the sound natural so <strong>the music stays clear. <\/strong>The attached filter reduces sound levels by 18-20dB (or 27dB when you use Loop Mute) <strong>keeping it all at a safer volume<\/strong>. <\/p>",
            "page": ""
          }
        },
        "2c00545b-7123-4081-aa4f-56cd3abab0b6": {
          "type": "collapsible_row",
          "settings": {
            "heading": "Look good",
            "icon": "check_mark",
            "row_content": "<p>Loop earplugs are <strong>designed with style<\/strong> and fit discreetly in your ear. Choose from a range of colors and wear them with confidence.<\/p>",
            "page": ""
          }
        },
        "ec977605-d721-4bc9-b58f-5864893bfe7f": {
          "type": "collapsible_row",
          "settings": {
            "heading": "Feel good",
            "icon": "check_mark",
            "row_content": "<p>They use memory foam and silicone tips, making them the most <strong>comfortable<\/strong> earplugs for concerts<strong>. <\/strong>They’ll stay put too – whether you’re dancing or headbanging.<\/p>",
            "page": ""
          }
        }
      },
      "block_order": [
        "template--15748392779972__9ed4066c-a046-482b-9f08-cfb717d13789-1666090534a02685d6-0",
        "2c00545b-7123-4081-aa4f-56cd3abab0b6",
        "ec977605-d721-4bc9-b58f-5864893bfe7f"
      ],
      "settings": {
        "caption": "",
        "heading": "Loop Experience Pro Earplugs",
        "heading_size": "h1",
        "heading_alignment": "center",
        "layout": "none",
        "color_scheme": "background-1",
        "container_color_scheme": "background-2",
        "open_first_collapsible_row": false,
        "image_ratio": "adapt",
        "desktop_layout": "image_second",
        "padding_top": 44,
        "padding_bottom": 44
      }
    },
    "1645638549e3f46616": {
      "type": "multicolumn",
      "blocks": {
        "1645638549ea471427-0": {
          "type": "column",
          "settings": {
            "video": "",
            "title": "“Listening to loud bands in small venues is now possible. I wish I had them when I went to see The Stranglers!”",
            "col_heading_font_size": 20,
            "text": "<p><em>- Melanie W.<\/em><\/p>",
            "text_color": "#9c9c9c",
            "founder_text": "",
            "founder_color": "#757470",
            "link_label": "",
            "link": ""
          }
        },
        "9441c346-d2dd-4a70-8da3-73666c31c516": {
          "type": "column",
          "disabled": true,
          "settings": {
            "video": "",
            "title": "Column",
            "col_heading_font_size": 20,
            "text": "<p>Pair text with an image to focus on your chosen product, collection, or blog post. Add details on availability, style, or even provide a review.<\/p>",
            "text_color": "#9c9c9c",
            "founder_text": "",
            "founder_color": "#757470",
            "link_label": "",
            "link": ""
          }
        }
      },
      "block_order": [
        "1645638549ea471427-0",
        "9441c346-d2dd-4a70-8da3-73666c31c516"
      ],
      "settings": {
        "title": "",
        "heading_size": "h1",
        "heading_center": false,
        "image_width": "full",
        "image_ratio": "adapt",
        "image_size": 100,
        "columns_desktop": 3,
        "column_alignment": "center",
        "background_style": "none",
        "button_label": "",
        "button_bgcolor_1": "",
        "button_txtcolor_1": "",
        "button_link": "",
        "color_scheme": "#fff",
        "heading_max_width": 70,
        "sub_heading_max_width": 70,
        "columns_mobile": "1",
        "swipe_on_mobile": false,
        "padding_top": 28,
        "padding_bottom": 28
      }
    },
    "dc274845-7eb9-41de-a2c0-575dfd91f1d1": {
      "type": "rich-text",
      "blocks": {
        "template--15751466811588__dc274845-7eb9-41de-a2c0-575dfd91f1d1-1666095395e4ba86dc-0": {
          "type": "heading",
          "settings": {
            "heading": "Crystal-clear concerts",
            "heading_size": "h1"
          }
        },
        "template--15751466811588__dc274845-7eb9-41de-a2c0-575dfd91f1d1-1666095395e4ba86dc-1": {
          "type": "text",
          "settings": {
            "text": "<p>Take them with you to your next concert and experience it for yourself. They reduce noise – but you won’t miss a thing.<\/p>",
            "description_padding": 10
          }
        },
        "ba69e20b-737e-469f-a39f-48d43fb9c33b": {
          "type": "button",
          "settings": {
            "button_label": "Earplugs for concerts",
            "button_link": "shopify:\/\/products\/experience",
            "button_bgcolor_1": "",
            "button_txtcolor_1": "",
            "button_style_secondary": false,
            "button_label_2": "",
            "button_link_2": "",
            "button_bgcolor_2": "",
            "button_txtcolor_2": "",
            "button_style_secondary_2": false,
            "button_padding": 32
          }
        }
      },
      "block_order": [
        "template--15751466811588__dc274845-7eb9-41de-a2c0-575dfd91f1d1-1666095395e4ba86dc-0",
        "template--15751466811588__dc274845-7eb9-41de-a2c0-575dfd91f1d1-1666095395e4ba86dc-1",
        "ba69e20b-737e-469f-a39f-48d43fb9c33b"
      ],
      "settings": {
        "desktop_content_position": "center",
        "content_alignment": "center",
        "color_scheme": "background-1",
        "full_width": true,
        "decription_max_width": 100,
        "padding_top": 44,
        "padding_bottom": 44
      }
    },
    "f4a2fc7a-dabb-4bed-824d-7d852d3a23db": {
      "type": "rich-text",
      "blocks": {
        "template--15751466811588__f4a2fc7a-dabb-4bed-824d-7d852d3a23db-1667917942199e3ee8-0": {
          "type": "heading",
          "settings": {
            "heading": "100 days free return",
            "heading_size": "h2"
          }
        },
        "template--15751466811588__f4a2fc7a-dabb-4bed-824d-7d852d3a23db-1667917942199e3ee8-1": {
          "type": "text",
          "settings": {
            "text": "<p>You’ll love them – but you can easily give them back if you’re not a fan.<\/p>",
            "description_padding": 32
          }
        }
      },
      "block_order": [
        "template--15751466811588__f4a2fc7a-dabb-4bed-824d-7d852d3a23db-1667917942199e3ee8-0",
        "template--15751466811588__f4a2fc7a-dabb-4bed-824d-7d852d3a23db-1667917942199e3ee8-1"
      ],
      "settings": {
        "desktop_content_position": "center",
        "content_alignment": "center",
        "color_scheme": "background-1",
        "full_width": true,
        "decription_max_width": 100,
        "padding_top": 40,
        "padding_bottom": 52
      }
    },
    "cf641fcb-fba6-4a2b-a002-e9613d506ee4": {
      "type": "rich-text",
      "blocks": {
        "template--15751466811588__cf641fcb-fba6-4a2b-a002-e9613d506ee4-166738685072cd3a65-0": {
          "type": "heading",
          "settings": {
            "heading": "Related blogposts",
            "heading_size": "h1"
          }
        }
      },
      "block_order": [
        "template--15751466811588__cf641fcb-fba6-4a2b-a002-e9613d506ee4-166738685072cd3a65-0"
      ],
      "settings": {
        "desktop_content_position": "center",
        "content_alignment": "center",
        "color_scheme": "background-1",
        "full_width": true,
        "decription_max_width": 100,
        "padding_top": 20,
        "padding_bottom": 20
      }
    },
    "ff151653-8d0e-442b-8fa6-be85c90742bd": {
      "type": "loop-featured-article",
      "blocks": {
        "909c8608-0244-4ccf-be90-132d2be3ab80": {
          "type": "select",
          "settings": {
            "article": "blog\/how-to-avoid-hearing-damage"
          }
        },
        "198b00de-92d6-4b11-8a4d-d4a533ec9f0c": {
          "type": "select",
          "settings": {
            "article": "blog\/how-to-stop-ringing-ears-after-a-concert"
          }
        },
        "012e94a2-e962-4144-9a0c-ffe96ce379e5": {
          "type": "select",
          "settings": {
            "article": "blog\/which-loop-earplugs-are-right-for-me"
          }
        }
      },
      "block_order": [
        "909c8608-0244-4ccf-be90-132d2be3ab80",
        "198b00de-92d6-4b11-8a4d-d4a533ec9f0c",
        "012e94a2-e962-4144-9a0c-ffe96ce379e5"
      ],
      "settings": {
        "columns_size": 3,
        "padding_top": 0,
        "padding_bottom": 0
      }
    },
    "39b5e74d-dcaf-42c3-8031-246d3c9446f7": {
      "type": "rich-text",
      "blocks": {
        "d5607a09-6c2c-436e-9b28-ae7f0304c7a9": {
          "type": "button",
          "settings": {
            "button_label": "All blog posts",
            "button_link": "shopify:\/\/blogs\/blog",
            "button_bgcolor_1": "#000000",
            "button_txtcolor_1": "",
            "button_style_secondary": false,
            "button_label_2": "",
            "button_link_2": "https:\/\/www.loopearplugs.com\/blogs\/blog",
            "button_bgcolor_2": "#000000",
            "button_txtcolor_2": "",
            "button_style_secondary_2": false,
            "button_padding": 8
          }
        }
      },
      "block_order": [
        "d5607a09-6c2c-436e-9b28-ae7f0304c7a9"
      ],
      "settings": {
        "desktop_content_position": "center",
        "content_alignment": "center",
        "color_scheme": "background-1",
        "full_width": true,
        "decription_max_width": 100,
        "padding_top": 0,
        "padding_bottom": 0
      }
    },
    "254bd345-8b8c-45d1-bd38-51b37b5f5fce": {
      "type": "multicolumn",
      "blocks": {
        "template--15751466811588__254bd345-8b8c-45d1-bd38-51b37b5f5fce-1667917933d4f46e30-0": {
          "type": "column",
          "settings": {
            "video": "",
            "title": "“Really comfortable and great at lowering volume without muffling music.”",
            "col_heading_font_size": 20,
            "text": "<p><em>- Charlie H.<\/em><\/p>",
            "text_color": "#9C9C9C",
            "founder_text": "",
            "founder_color": "#757470",
            "link_label": "",
            "link": ""
          }
        },
        "template--15751466811588__254bd345-8b8c-45d1-bd38-51b37b5f5fce-1667917933d4f46e30-1": {
          "type": "column",
          "disabled": true,
          "settings": {
            "video": "",
            "title": "Column",
            "col_heading_font_size": 20,
            "text": "<p>Pair text with an image to focus on your chosen product, collection, or blog post. Add details on availability, style, or even provide a review.<\/p>",
            "text_color": "#9C9C9C",
            "founder_text": "",
            "founder_color": "#757470",
            "link_label": "",
            "link": ""
          }
        },
        "template--15751466811588__254bd345-8b8c-45d1-bd38-51b37b5f5fce-1667917933d4f46e30-2": {
          "type": "column",
          "disabled": true,
          "settings": {
            "video": "",
            "title": "Column",
            "col_heading_font_size": 20,
            "text": "<p>Pair text with an image to focus on your chosen product, collection, or blog post. Add details on availability, style, or even provide a review.<\/p>",
            "text_color": "#9C9C9C",
            "founder_text": "",
            "founder_color": "#757470",
            "link_label": "",
            "link": ""
          }
        }
      },
      "block_order": [
        "template--15751466811588__254bd345-8b8c-45d1-bd38-51b37b5f5fce-1667917933d4f46e30-0",
        "template--15751466811588__254bd345-8b8c-45d1-bd38-51b37b5f5fce-1667917933d4f46e30-1",
        "template--15751466811588__254bd345-8b8c-45d1-bd38-51b37b5f5fce-1667917933d4f46e30-2"
      ],
      "settings": {
        "title": "",
        "heading_size": "h1",
        "heading_center": false,
        "image_width": "full",
        "image_ratio": "adapt",
        "image_size": 100,
        "columns_desktop": 3,
        "column_alignment": "center",
        "background_style": "primary",
        "button_label": "",
        "button_bgcolor_1": "",
        "button_txtcolor_1": "",
        "button_link": "",
        "color_scheme": "background-1",
        "heading_max_width": 70,
        "sub_heading_max_width": 70,
        "columns_mobile": "1",
        "swipe_on_mobile": false,
        "padding_top": 28,
        "padding_bottom": 28
      }
    }
  },
  "order": [
    "main",
    "1645786349bb92c16e",
    "16457863188a1c84d3",
    "a509a09c-1018-4eb2-b12f-0f9203475dc6",
    "ad2c432f-2b38-47ef-9a80-5b253f5c2f56",
    "5baf8b65-901d-487b-b196-547e9054e979",
    "3a7b4a7e-81fd-498c-a497-8968c3a75f79",
    "10843f6a-ac93-4a2b-8b91-b657d7ca3b90",
    "e81e33a8-46eb-4508-a15a-090a843d5c31",
    "9ed4066c-a046-482b-9f08-cfb717d13789",
    "1645638549e3f46616",
    "dc274845-7eb9-41de-a2c0-575dfd91f1d1",
    "f4a2fc7a-dabb-4bed-824d-7d852d3a23db",
    "cf641fcb-fba6-4a2b-a002-e9613d506ee4",
    "ff151653-8d0e-442b-8fa6-be85c90742bd",
    "39b5e74d-dcaf-42c3-8031-246d3c9446f7",
    "254bd345-8b8c-45d1-bd38-51b37b5f5fce"
  ]
}
